{ "books": [
{
  "genre": "all",
  "date": "2026-01-11",
  "title": "Bulldog Drummond",
  "author": "H. C. McNeile",
  "summary": "A demobilized officer places a newspaper advert for adventure, and its response leads him to discover a conspiracy.",
  "coverUrl": "https://standardebooks.org/ebooks/h-c-mcneile/bulldog-drummond/downloads/cover.jpg",
  "entryUrl": "https://standardebooks.org/ebooks/h-c-mcneile/bulldog-drummond",
  "subjects": [
    "adventure",
    "fiction"
  ]
}
,
{
  "genre": "adventure",
  "date": "2026-01-11",
  "title": "When the World Shook",
  "author": "H. Rider Haggard",
  "summary": "A writer of adventure stories indulges in a sudden urge to travel to the islands of the Pacific, and soon finds himself shipwrecked on a remote South Sea island.",
  "coverUrl": "https://standardebooks.org/ebooks/h-rider-haggard/when-the-world-shook/downloads/cover.jpg",
  "entryUrl": "https://standardebooks.org/ebooks/h-rider-haggard/when-the-world-shook",
  "subjects": [
    "adventure",
    "fiction"
  ]
}
,
{
  "genre": "autobiography",
  "date": "2026-01-11",
  "title": "A Daughter of the Samurai",
  "author": "Etsu Inagaki Sugimoto",
  "summary": "The autobiography of Etsu Sugimoto, a girl born into a samurai family in a time of great cultural changes.",
  "coverUrl": "https://standardebooks.org/ebooks/etsu-inagaki-sugimoto/a-daughter-of-the-samurai/downloads/cover.jpg",
  "entryUrl": "https://standardebooks.org/ebooks/etsu-inagaki-sugimoto/a-daughter-of-the-samurai",
  "subjects": [
    "autobiography",
    "nonfiction"
  ]
}
,
{
  "genre": "biography",
  "date": "2026-01-11",
  "title": "Recollections of Full Years",
  "author": "Helen Herron Taft",
  "summary": "Helen Herron Taft, wife of William Howard Taft, the twenty-seventh President of the United States, recalls her life married to one of America’s most influential political figures.",
  "coverUrl": "https://standardebooks.org/ebooks/helen-herron-taft/recollections-of-full-years/downloads/cover.jpg",
  "entryUrl": "https://standardebooks.org/ebooks/helen-herron-taft/recollections-of-full-years",
  "subjects": [
    "biography",
    "memoir",
    "nonfiction",
    "travel"
  ]
}
,
{
  "genre": "childrens",
  "date": "2026-01-11",
  "title": "The Mystery of Cabin Island",
  "author": "Franklin W. Dixon",
  "summary": "A group of amateur detectives unravel the mystery of a missing stamps collection.",
  "coverUrl": "https://standardebooks.org/ebooks/franklin-w-dixon/the-mystery-of-cabin-island/downloads/cover.jpg",
  "entryUrl": "https://standardebooks.org/ebooks/franklin-w-dixon/the-mystery-of-cabin-island",
  "subjects": [
    "adventure",
    "childrens",
    "fiction",
    "mystery"
  ]
}
,
{
  "genre": "comedy",
  "date": "2026-01-11",
  "title": "Short Fiction",
  "author": "Edgar Allan Poe",
  "summary": "A collection of Edgar Allan Poe’s short fiction, ordered by date of publication.",
  "coverUrl": "https://standardebooks.org/ebooks/edgar-allan-poe/short-fiction/downloads/cover.jpg",
  "entryUrl": "https://standardebooks.org/ebooks/edgar-allan-poe/short-fiction",
  "subjects": [
    "adventure",
    "comedy",
    "horror",
    "mystery",
    "satire",
    "science_fiction",
    "shorts"
  ]
}
,
{
  "genre": "drama",
  "date": "2026-01-11",
  "title": "Ajax",
  "author": "Sophocles",
  "summary": "A great warrior descends into madness after being denied magical armor.",
  "coverUrl": "https://standardebooks.org/ebooks/sophocles/ajax/francis-storr/downloads/cover.jpg",
  "entryUrl": "https://standardebooks.org/ebooks/sophocles/ajax/francis-storr",
  "subjects": [
    "drama"
  ]
}
,
{
  "genre": "fantasy",
  "date": "2026-01-11",
  "title": "Phantastes",
  "author": "George MacDonald",
  "summary": "A young man awakes in Fairy Land, where he takes part in a series of strange adventures.",
  "coverUrl": "https://standardebooks.org/ebooks/george-macdonald/phantastes/downloads/cover.jpg",
  "entryUrl": "https://standardebooks.org/ebooks/george-macdonald/phantastes",
  "subjects": [
    "fantasy"
  ]
}
,
{
  "genre": "fiction",
  "date": "2026-01-11",
  "title": "The Bridal Wreath",
  "author": "Sigrid Undset",
  "summary": "In 14th-century Norway, a nobleman’s daughter grows up and faces passion, sin, and filial piety.",
  "coverUrl": "https://standardebooks.org/ebooks/sigrid-undset/the-bridal-wreath/charles-archer_j-s-scott/downloads/cover.jpg",
  "entryUrl": "https://standardebooks.org/ebooks/sigrid-undset/the-bridal-wreath/charles-archer_j-s-scott",
  "subjects": [
    "fiction"
  ]
}
,
{
  "genre": "horror",
  "date": "2026-01-11",
  "title": "Brood of the Witch-Queen",
  "author": "Sax Rohmer",
  "summary": "A father and son duo investigate a man who is wielding ancient Egyptian magic.",
  "coverUrl": "https://standardebooks.org/ebooks/sax-rohmer/brood-of-the-witch-queen/downloads/cover.jpg",
  "entryUrl": "https://standardebooks.org/ebooks/sax-rohmer/brood-of-the-witch-queen",
  "subjects": [
    "fiction",
    "horror"
  ]
}
,
{
  "genre": "memoir",
  "date": "2026-01-11",
  "title": "A Personal Record",
  "author": "Joseph Conrad",
  "summary": "Conrad recounts his childhood in Poland, his sailing experiences, and the work on his debut novel.",
  "coverUrl": "https://standardebooks.org/ebooks/joseph-conrad/a-personal-record/downloads/cover.jpg",
  "entryUrl": "https://standardebooks.org/ebooks/joseph-conrad/a-personal-record",
  "subjects": [
    "memoir",
    "nonfiction"
  ]
}
,
{
  "genre": "mystery",
  "date": "2026-01-11",
  "title": "The Insidious Dr. Fu-Manchu",
  "author": "Sax Rohmer",
  "summary": "An intrepid detective hunts the criminal mastermind Fu-Manchu through early 20th-century London.",
  "coverUrl": "https://standardebooks.org/ebooks/sax-rohmer/the-insidious-dr-fu-manchu/downloads/cover.jpg",
  "entryUrl": "https://standardebooks.org/ebooks/sax-rohmer/the-insidious-dr-fu-manchu",
  "subjects": [
    "fiction",
    "mystery"
  ]
}
,
{
  "genre": "nonfiction",
  "date": "2026-01-11",
  "title": "Red Dusk and the Morrow",
  "author": "Paul Dukes",
  "summary": "A newly-minted secret agent is sent to pick up the pieces of Britain’s spy networks after they are shattered by the Red Terror.",
  "coverUrl": "https://standardebooks.org/ebooks/paul-dukes/red-dusk-and-the-morrow/downloads/cover.jpg",
  "entryUrl": "https://standardebooks.org/ebooks/paul-dukes/red-dusk-and-the-morrow",
  "subjects": [
    "memoir",
    "nonfiction"
  ]
}
,
{
  "genre": "philosophy",
  "date": "2026-01-11",
  "title": "An Inquiry Into the Accordancy of War with the Principles of Christianity",
  "author": "Jonathan Dymond",
  "summary": "Dymond argues that war is incompatible with the teachings of Christianity.",
  "coverUrl": "https://standardebooks.org/ebooks/jonathan-dymond/an-inquiry-into-the-accordancy-of-war-with-the-principles-of-christianity/downloads/cover.jpg",
  "entryUrl": "https://standardebooks.org/ebooks/jonathan-dymond/an-inquiry-into-the-accordancy-of-war-with-the-principles-of-christianity",
  "subjects": [
    "philosophy",
    "spirituality"
  ]
}
,
{
  "genre": "poetry",
  "date": "2026-01-11",
  "title": "Poetry",
  "author": "Georgia Douglas Johnson",
  "summary": "A collection of poems by Georgia Douglas Johnson.",
  "coverUrl": "https://standardebooks.org/ebooks/georgia-douglas-johnson/poetry/downloads/cover.jpg",
  "entryUrl": "https://standardebooks.org/ebooks/georgia-douglas-johnson/poetry",
  "subjects": [
    "poetry"
  ]
}
,
{
  "genre": "satire",
  "date": "2026-01-11",
  "title": "Northanger Abbey",
  "author": "Jane Austen",
  "summary": "A young girl with an overactive imagination comes of age.",
  "coverUrl": "https://standardebooks.org/ebooks/jane-austen/northanger-abbey/downloads/cover.jpg",
  "entryUrl": "https://standardebooks.org/ebooks/jane-austen/northanger-abbey",
  "subjects": [
    "fiction",
    "satire"
  ]
}
,
{
  "genre": "science_fiction",
  "date": "2026-01-11",
  "title": "The Inheritors",
  "author": "Joseph Conrad",
  "summary": "A young writer dabbling in journalism meets a strange, otherworldly woman with long-term political goals.",
  "coverUrl": "https://standardebooks.org/ebooks/joseph-conrad_ford-madox-ford/the-inheritors/downloads/cover.jpg",
  "entryUrl": "https://standardebooks.org/ebooks/joseph-conrad_ford-madox-ford/the-inheritors",
  "subjects": [
    "science_fiction"
  ]
}
,
{
  "genre": "shorts",
  "date": "2026-01-11",
  "title": "Poirot Investigates",
  "author": "Agatha Christie",
  "summary": "A calculating Belgian detective and his wide-eyed companion investigate and solve a series of mysteries.",
  "coverUrl": "https://standardebooks.org/ebooks/agatha-christie/poirot-investigates/downloads/cover.jpg",
  "entryUrl": "https://standardebooks.org/ebooks/agatha-christie/poirot-investigates",
  "subjects": [
    "mystery",
    "shorts"
  ]
}
,
{
  "genre": "spirituality",
  "date": "2026-01-11",
  "title": "The Story of My Experiments with Truth",
  "author": "Mahatma Gandhi",
  "summary": "Gandhi relates his life experiences from his birth in Gujarat in 1869 through the Indian National Congress of 1915.",
  "coverUrl": "https://standardebooks.org/ebooks/mahatma-gandhi/the-story-of-my-experiments-with-truth/mahadev-desai/downloads/cover.jpg",
  "entryUrl": "https://standardebooks.org/ebooks/mahatma-gandhi/the-story-of-my-experiments-with-truth/mahadev-desai",
  "subjects": [
    "autobiography",
    "memoir",
    "nonfiction",
    "philosophy",
    "spirituality"
  ]
}
,
{
  "genre": "travel",
  "date": "2026-01-11",
  "title": "My Four Weeks in France",
  "author": "Ring Lardner",
  "summary": "A sports columnist and humorist travels to France as a war correspondent during World War I and recounts his experiences on the assignment.",
  "coverUrl": "https://standardebooks.org/ebooks/ring-lardner/my-four-weeks-in-france/downloads/cover.jpg",
  "entryUrl": "https://standardebooks.org/ebooks/ring-lardner/my-four-weeks-in-france",
  "subjects": [
    "comedy",
    "memoir",
    "nonfiction",
    "travel"
  ]
}
] }
